nlp-16a/Hardware/alu_ctrl/decoder/Ctrl4/decoder_ctrl4.v
module decode_ctrl4(Ctrl4,INTERNAL_MOV,ADDRESS_MODE,INTERNAL_INC_DEC,INTERNAL_DEC,Ctrl4_out);
    input Ctrl4,INTERNAL_MOV,ADDRESS_MODE,INTERNAL_INC_DEC,INTERNAL_DEC;
    output Ctrl4_out;
    wire tmp1,tmp2,tmp3;
    NAND NAND1(Ctrl4,INTERNAL_MOV,tmp1);
    
    NAND NAND2(INTERNAL_INC_DEC,INTERNAL_INC_DEC,tmp2);
    NAND NAND3(tmp2,INTERNAL_DEC,tmp3);

    NAND NAND4(tmp1,tmp3,Ctrl4_out);
endmodule

nlp-16a/Hardware/alu_ctrl/decoder/Ctrl4/Ctrl4.v
module AND(
  a, b, x
);

  input a, b;
  output x;

  assign x = a & b;

endmodule // AND

module NAND(a, b, y);
    input a, b;
    output y;
    wire tmp;
    AND AND(a,b,tmp);

    assign y = ~tmp;
endmodule



module test_tb ();

    parameter clk_period_p = 10;

    reg Ctrl4,INTERNAL_MOV,ADDRESS_MODE,INTERNAL_INC_DEC,INTERNAL_DEC;
    wire [0:0] out_Ctrl4;

    decode_ctrl4 decode_ctrl4(Ctrl4,INTERNAL_MOV,ADDRESS_MODE,INTERNAL_INC_DEC,INTERNAL_DEC,Ctrl4_out);

    initial begin
        $dumpfile("test.vcd");
        $dumpvars(0);
        $monitor("%t: Ctrl4 = %b, INTERNAL_MOV =%b, ADDRESS_MODE = %b, INTERNAL_INC_DEC = %b, INTERNAL_DEC = %b, Ctrl4_out = %b", $time,Ctrl4,INTERNAL_MOV,ADDRESS_MODE,INTERNAL_INC_DEC,INTERNAL_DEC,Ctrl4_out);
        
        //通常モード
        Ctrl4 = 0;
        INTERNAL_MOV = 1;
        ADDRESS_MODE = 1;
        INTERNAL_INC_DEC = 1;
        INTERNAL_DEC = 1;
        #clk_period_p;

        Ctrl4 = 1;
        INTERNAL_MOV = 1;
        ADDRESS_MODE = 1;
        INTERNAL_INC_DEC = 1;
        INTERNAL_DEC = 1;
        #clk_period_p;

        //内部処理 MOV
        Ctrl4 = 0;
        INTERNAL_MOV = 0;
        ADDRESS_MODE = 1;
        INTERNAL_INC_DEC = 1;
        INTERNAL_DEC = 1;
        #clk_period_p;

        Ctrl4 = 1;
        INTERNAL_MOV = 0;
        ADDRESS_MODE = 1;
        INTERNAL_INC_DEC = 1;
        INTERNAL_DEC = 1;
        #clk_period_p;

        //内部処理 INC
        Ctrl4 = 0;
        INTERNAL_MOV = 0;
        ADDRESS_MODE = 1;
        INTERNAL_INC_DEC = 0;
        INTERNAL_DEC = 1;
        #clk_period_p;

        Ctrl4 = 1;
        INTERNAL_MOV = 0;
        ADDRESS_MODE = 1;
        INTERNAL_INC_DEC = 0;
        INTERNAL_DEC = 1;
        #clk_period_p;

        //内部処理 INC
        Ctrl4 = 0;
        INTERNAL_MOV = 0;
        ADDRESS_MODE = 1;
        INTERNAL_INC_DEC = 0;
        INTERNAL_DEC = 0;
        #clk_period_p;

        Ctrl4 = 1;
        INTERNAL_MOV = 0;
        ADDRESS_MODE = 1;
        INTERNAL_INC_DEC = 0;
        INTERNAL_DEC = 0;
        #clk_period_p;

      //アドレス演算モード//
        //通常モード
        Ctrl4 = 0;
        INTERNAL_MOV = 1;
        ADDRESS_MODE = 0;
        INTERNAL_INC_DEC = 1;
        INTERNAL_DEC = 1;
        #clk_period_p;
        Ctrl4 = 1;
        INTERNAL_MOV = 1;
        ADDRESS_MODE = 0;
        INTERNAL_INC_DEC = 1;
        INTERNAL_DEC = 1;
        #clk_period_p;
        //内部処理 MOV
        Ctrl4 = 0;
        INTERNAL_MOV = 0;
        ADDRESS_MODE = 0;
        INTERNAL_INC_DEC = 1;
        INTERNAL_DEC = 1;
        #clk_period_p;

        Ctrl4 = 1;
        INTERNAL_MOV = 0;
        ADDRESS_MODE = 0;
        INTERNAL_INC_DEC = 1;
        INTERNAL_DEC = 1;
        #clk_period_p;

        //内部処理 INC
        Ctrl4 = 0;
        INTERNAL_MOV = 0;
        ADDRESS_MODE = 0;
        INTERNAL_INC_DEC = 0;
        INTERNAL_DEC = 1;
        #clk_period_p;

        Ctrl4 = 1;
        INTERNAL_MOV = 0;
        ADDRESS_MODE = 0;
        INTERNAL_INC_DEC = 0;
        INTERNAL_DEC = 1;
        #clk_period_p;

        //内部処理 INC
        Ctrl4 = 0;
        INTERNAL_MOV = 0;
        ADDRESS_MODE = 0;
        INTERNAL_INC_DEC = 0;
        INTERNAL_DEC = 0;
        #clk_period_p;

        Ctrl4 = 1;
        INTERNAL_MOV = 0;
        ADDRESS_MODE = 0;
        INTERNAL_INC_DEC = 0;
        INTERNAL_DEC = 0;
        #clk_period_p;


        $finish;
    end
endmodule

nlp-16a/Hardware/alu_ctrl/decoder/Ctrl4/test.vcd
$date
	Mon Jul 17 22:24:47 2023
$end
$version
	Icarus Verilog
$end
$timescale
	1s
$end
$scope module test_tb $end
$var wire 1 ! Ctrl4_out $end
$var parameter 32 " clk_period_p $end
$var reg 1 # ADDRESS_MODE $end
$var reg 1 $ Ctrl4 $end
$var reg 1 % INTERNAL_DEC $end
$var reg 1 & INTERNAL_INC_DEC $end
$var reg 1 ' INTERNAL_MOV $end
$scope module decode_ctrl4 $end
$var wire 1 # ADDRESS_MODE $end
$var wire 1 $ Ctrl4 $end
$var wire 1 % INTERNAL_DEC $end
$var wire 1 & INTERNAL_INC_DEC $end
$var wire 1 ' INTERNAL_MOV $end
$var wire 1 ( tmp3 $end
$var wire 1 ) tmp2 $end
$var wire 1 * tmp1 $end
$var wire 1 ! Ctrl4_out $end
$scope module NAND1 $end
$var wire 1 $ a $end
$var wire 1 ' b $end
$var wire 1 * y $end
$var wire 1 + tmp $end
$scope module AND $end
$var wire 1 $ a $end
$var wire 1 ' b $end
$var wire 1 + x $end
$upscope $end
$upscope $end
$scope module NAND2 $end
$var wire 1 & a $end
$var wire 1 & b $end
$var wire 1 ) y $end
$var wire 1 , tmp $end
$scope module AND $end
$var wire 1 & a $end
$var wire 1 & b $end
$var wire 1 , x $end
$upscope $end
$upscope $end
$scope module NAND3 $end
$var wire 1 ) a $end
$var wire 1 % b $end
$var wire 1 ( y $end
$var wire 1 - tmp $end
$scope module AND $end
$var wire 1 ) a $end
$var wire 1 % b $end
$var wire 1 - x $end
$upscope $end
$upscope $end
$scope module NAND4 $end
$var wire 1 * a $end
$var wire 1 ( b $end
$var wire 1 ! y $end
$var wire 1 . tmp $end
$scope module AND $end
$var wire 1 * a $end
$var wire 1 ( b $end
$var wire 1 . x $end
$upscope $end
$upscope $end
$upscope $end
$upscope $end
$enddefinitions $end
$comment Show the parameter values. $end
$dumpall
b1010 "
$end
#0
$dumpvars
1.
0-
1,
0+
1*
0)
1(
1'
1&
1%
0$
1#
0!
$end
#10
1!
0.
0*
1+
1$
#20
0!
1.
1*
0+
0'
0$
#30
1$
#40
1!
0.
0(
1-
1)
0,
0&
0$
#50
1$
#60
0!
1.
1(
0-
0%
0$
#70
1$
#80
0!
1.
1(
0)
0-
1,
1%
1&
0#
1'
0$
#90
1!
0.
0*
1+
1$
#100
0!
1.
1*
0+
0'
0$
#110
1$
#120
1!
0.
0(
1-
1)
0,
0&
0$
#130
1$
#140
0!
1.
1(
0-
0%
0$
#150
1$
