nlp-16a/Hardware/alu_ctrl/decoder/ALU1/decoder_ALU1.v
module decode_ALU1(Ctrl0,Ctrl1,Ctrl2,Ctrl3,Ctrl4,Ctrl5,c_flag,ALU1_out);
    input Ctrl0,Ctrl1,Ctrl2,Ctrl3,Ctrl4,Ctrl5,c_flag;
    output ALU1_out;
    wire tmp1,tmp2;
    NAND NAND1(~Ctrl0,~Ctrl1,tmp1);
    NAND NAND2(tmp1,tmp1,tmp2);
    NAND NAND3(tmp2,Ctrl2,ALU1_out);
endmodule

nlp-16a/Hardware/alu_ctrl/decoder/ALU1/ALU1.v
module AND(
  a, b, x
);

  input a, b;
  output x;

  assign x = a & b;

endmodule // AND

module NAND(a, b, y);
    input a, b;
    output y;
    wire tmp;
    AND AND(a,b,tmp);

    assign y = ~tmp;
endmodule



module test_tb ();

    parameter clk_period_p = 10;

    reg Ctrl0,Ctrl1,Ctrl2,Ctrl3,Ctrl4,Ctrl5,c_flag;
    wire [0:0] out_Ctrl0;

    decode_ALU1 decode_ALU1(Ctrl0,Ctrl1,Ctrl2,Ctrl3,Ctrl4,Ctrl5,c_flag,ALU1_out);

    initial begin
        $dumpfile("test.vcd");
        $dumpvars(0);
        $monitor("%t: Ctrl0 = %b, Ctrl1 = %b, Ctrl2 = %b, Ctrl3 = %b, Ctrl4 = %b, Ctrl5 = %b, c_flag = %b, ALU1_out = %b, ", $time,Ctrl0,Ctrl1,Ctrl2,Ctrl3,Ctrl4,Ctrl5,c_flag,ALU1_out);
        //ADD
        Ctrl0 = 0;
        Ctrl1 = 1;
        Ctrl2 = 0;
        Ctrl3 = 0;
        Ctrl4 = 1;
        Ctrl5 = 0;
        #clk_period_p;
        //SUB
        Ctrl0 = 0;
        Ctrl1 = 1;
        Ctrl2 = 0;
        Ctrl3 = 0;
        Ctrl4 = 0;
        Ctrl5 = 1;
        #clk_period_p;
        //OR
        Ctrl0 = 0;
        Ctrl1 = 0;
        Ctrl2 = 1;
        Ctrl3 = 0;
        Ctrl4 = 1;
        Ctrl5 = 0;
        #clk_period_p;
        //NOT
        Ctrl0 = 0;
        Ctrl1 = 0;
        Ctrl2 = 1;
        Ctrl3 = 1;
        Ctrl4 = 0;
        Ctrl5 = 0;
        #clk_period_p;
        //XOR
        Ctrl0 = 0;
        Ctrl1 = 0;
        Ctrl2 = 1;
        Ctrl3 = 1;
        Ctrl4 = 1;
        Ctrl5 = 0;
        #clk_period_p;
        //AND
        Ctrl0 = 0;
        Ctrl1 = 0;
        Ctrl2 = 0;
        Ctrl3 = 1;
        Ctrl4 = 1;
        Ctrl5 = 0;
        #clk_period_p;
        //MOV
        Ctrl0 = 0;
        Ctrl1 = 0;
        Ctrl2 = 0;
        Ctrl3 = 0;
        Ctrl4 = 0;
        Ctrl5 = 0;
        #clk_period_p;
        //INC
        Ctrl0 = 0;
        Ctrl1 = 1;
        Ctrl2 = 1;
        Ctrl3 = 0;
        Ctrl4 = 1;
        Ctrl5 = 1;
        #clk_period_p;
        //DEC
        Ctrl0 = 0;
        Ctrl1 = 1;
        Ctrl2 = 1;
        Ctrl3 = 0;
        Ctrl4 = 0;
        Ctrl5 = 0;
        #clk_period_p;
        //SLA
        Ctrl0 = 1;
        Ctrl1 = 0;
        Ctrl2 = 0;
        Ctrl3 = 1;
        Ctrl4 = 0;
        Ctrl5 = 0;
        #clk_period_p;
        //SLL
        Ctrl0 = 1;
        Ctrl1 = 0;
        Ctrl2 = 0;
        Ctrl3 = 0;
        Ctrl4 = 0;
        Ctrl5 = 0;
        #clk_period_p;
        //ROL
        Ctrl0 = 1;
        Ctrl1 = 0;
        Ctrl2 = 0;
        Ctrl3 = 0;
        Ctrl4 = 1;
        Ctrl5 = 0;
        #clk_period_p;
        //SRA
        Ctrl0 = 1;
        Ctrl1 = 0;
        Ctrl2 = 1;
        Ctrl3 = 1;
        Ctrl4 = 0;
        Ctrl5 = 0;
        #clk_period_p;
        //SRL
        Ctrl0 = 1;
        Ctrl1 = 0;
        Ctrl2 = 1;
        Ctrl3 = 0;
        Ctrl4 = 0;
        Ctrl5 = 0;
        #clk_period_p;
        //ROR
        Ctrl0 = 1;
        Ctrl1 = 0;
        Ctrl2 = 1;
        Ctrl3 = 0;
        Ctrl4 = 1;
        Ctrl5 = 0;
        #clk_period_p;

        $finish;
    end
endmodule

nlp-16a/Hardware/alu_ctrl/decoder/ALU1/test.vcd
$date
	Mon Jul 17 22:51:37 2023
$end
$version
	Icarus Verilog
$end
$timescale
	1s
$end
$scope module test_tb $end
$var wire 1 ! ALU1_out $end
$var parameter 32 " clk_period_p $end
$var reg 1 # Ctrl0 $end
$var reg 1 $ Ctrl1 $end
$var reg 1 % Ctrl2 $end
$var reg 1 & Ctrl3 $end
$var reg 1 ' Ctrl4 $end
$var reg 1 ( Ctrl5 $end
$var reg 1 ) c_flag $end
$scope module decode_ALU1 $end
$var wire 1 # Ctrl0 $end
$var wire 1 $ Ctrl1 $end
$var wire 1 % Ctrl2 $end
$var wire 1 & Ctrl3 $end
$var wire 1 ' Ctrl4 $end
$var wire 1 ( Ctrl5 $end
$var wire 1 ) c_flag $end
$var wire 1 * tmp2 $end
$var wire 1 + tmp1 $end
$var wire 1 ! ALU1_out $end
$scope module NAND1 $end
$var wire 1 , a $end
$var wire 1 - b $end
$var wire 1 + y $end
$var wire 1 . tmp $end
$scope module AND $end
$var wire 1 , a $end
$var wire 1 - b $end
$var wire 1 . x $end
$upscope $end
$upscope $end
$scope module NAND2 $end
$var wire 1 + a $end
$var wire 1 + b $end
$var wire 1 * y $end
$var wire 1 / tmp $end
$scope module AND $end
$var wire 1 + a $end
$var wire 1 + b $end
$var wire 1 / x $end
$upscope $end
$upscope $end
$scope module NAND3 $end
$var wire 1 * a $end
$var wire 1 % b $end
$var wire 1 ! y $end
$var wire 1 0 tmp $end
$scope module AND $end
$var wire 1 * a $end
$var wire 1 % b $end
$var wire 1 0 x $end
$upscope $end
$upscope $end
$upscope $end
$upscope $end
$enddefinitions $end
$comment Show the parameter values. $end
$dumpall
b1010 "
$end
#0
$dumpvars
00
1/
0.
0-
1,
1+
0*
x)
0(
1'
0&
0%
1$
0#
1!
$end
#10
1(
0'
#20
0!
10
1*
0/
0+
1.
1-
0(
1'
1%
0$
#30
0'
1&
#40
1'
#50
1!
00
0%
#60
0'
0&
#70
0*
1/
1+
1!
0.
00
0-
1(
1'
1%
1$
#80
0(
0'
#90
1-
0,
1&
0%
0$
1#
#100
0&
#110
1'
#120
0'
1&
1%
#130
0&
#140
1'
