nlp-16a/Hardware/alu_ctrl/decoder/Ctrl0/decoder_ctrl0.v
module decode_ctrl0(Ctrl0,INTERNAL_MOV,ADDRESS_MODE,INTERNAL_INC_DEC,INTERNAL_DEC,Ctrl0_out);
    input Ctrl0,INTERNAL_MOV,ADDRESS_MODE,INTERNAL_INC_DEC,INTERNAL_DEC;
    output Ctrl0_out;
    wire tmp1,tmp2,tmp3;
    NAND NAND1(Ctrl0,ADDRESS_MODE,tmp1);
    NAND NAND2(tmp1,tmp1,tmp2);
    NAND NAND3(tmp2,INTERNAL_MOV,tmp3);
    NAND NAND4(tmp3,tmp3,Ctrl0_out);
endmodule

nlp-16a/Hardware/alu_ctrl/decoder/Ctrl5/Ctrl5.v
module AND(
  a, b, x
);

  input a, b;
  output x;

  assign x = a & b;

endmodule // AND

module NAND(a, b, y);
    input a, b;
    output y;
    wire tmp;
    AND AND(a,b,tmp);

    assign y = ~tmp;
endmodule



module test_tb ();

    parameter clk_period_p = 10;

    reg Ctrl0,INTERNAL_MOV,ADDRESS_MODE,INTERNAL_INC_DEC,INTERNAL_DEC;
    wire [0:0] out_Ctrl0;

    decode_ctrl0 decode_ctrl0(Ctrl0,INTERNAL_MOV,ADDRESS_MODE,INTERNAL_INC_DEC,INTERNAL_DEC,Ctrl0_out);

    initial begin
        $dumpfile("test.vcd");
        $dumpvars(0);
        $monitor("%t: Ctrl0 = %b, INTERNAL_MOV =%b, ADDRESS_MODE = %b, INTERNAL_INC_DEC = %b, INTERNAL_DEC = %b, Ctrl0_out = %b", $time,Ctrl0,INTERNAL_MOV,ADDRESS_MODE,INTERNAL_INC_DEC,INTERNAL_DEC,Ctrl0_out);
        //通常モード
        Ctrl0 = 0;
        INTERNAL_MOV = 1;
        ADDRESS_MODE = 1;
        INTERNAL_INC_DEC = 1;
        INTERNAL_DEC = 1;
        #clk_period_p;

        Ctrl0 = 1;
        INTERNAL_MOV = 1;
        ADDRESS_MODE = 1;
        INTERNAL_INC_DEC = 1;
        INTERNAL_DEC = 1;
        #clk_period_p;

        //内部処理 MOV
        Ctrl0 = 0;
        INTERNAL_MOV = 0;
        ADDRESS_MODE = 1;
        INTERNAL_INC_DEC = 1;
        INTERNAL_DEC = 1;
        #clk_period_p;

        Ctrl0 = 1;
        INTERNAL_MOV = 0;
        ADDRESS_MODE = 1;
        INTERNAL_INC_DEC = 1;
        INTERNAL_DEC = 1;
        #clk_period_p;

        //内部処理 INC
        Ctrl0 = 0;
        INTERNAL_MOV = 0;
        ADDRESS_MODE = 1;
        INTERNAL_INC_DEC = 0;
        INTERNAL_DEC = 1;
        #clk_period_p;

        Ctrl0 = 1;
        INTERNAL_MOV = 0;
        ADDRESS_MODE = 1;
        INTERNAL_INC_DEC = 0;
        INTERNAL_DEC = 1;
        #clk_period_p;

        //内部処理 INC
        Ctrl0 = 0;
        INTERNAL_MOV = 0;
        ADDRESS_MODE = 1;
        INTERNAL_INC_DEC = 0;
        INTERNAL_DEC = 0;
        #clk_period_p;

        Ctrl0 = 1;
        INTERNAL_MOV = 0;
        ADDRESS_MODE = 1;
        INTERNAL_INC_DEC = 0;
        INTERNAL_DEC = 0;
        #clk_period_p;

      //アドレス演算モード//

        //内部処理 MOV
        Ctrl0 = 0;
        INTERNAL_MOV = 0;
        ADDRESS_MODE = 1;
        INTERNAL_INC_DEC = 1;
        INTERNAL_DEC = 1;
        #clk_period_p;

        Ctrl0 = 1;
        INTERNAL_MOV = 0;
        ADDRESS_MODE = 1;
        INTERNAL_INC_DEC = 1;
        INTERNAL_DEC = 1;
        #clk_period_p;

        //内部処理 INC
        Ctrl0 = 0;
        INTERNAL_MOV = 0;
        ADDRESS_MODE = 1;
        INTERNAL_INC_DEC = 0;
        INTERNAL_DEC = 1;
        #clk_period_p;

        Ctrl0 = 1;
        INTERNAL_MOV = 0;
        ADDRESS_MODE = 1;
        INTERNAL_INC_DEC = 0;
        INTERNAL_DEC = 1;
        #clk_period_p;

        //内部処理 INC
        Ctrl0 = 0;
        INTERNAL_MOV = 0;
        ADDRESS_MODE = 1;
        INTERNAL_INC_DEC = 0;
        INTERNAL_DEC = 0;
        #clk_period_p;

        Ctrl0 = 1;
        INTERNAL_MOV = 0;
        ADDRESS_MODE = 1;
        INTERNAL_INC_DEC = 0;
        INTERNAL_DEC = 0;
        #clk_period_p;

        $finish;
    end
endmodule

nlp-16a/Hardware/alu_ctrl/decoder/Ctrl5/test.vcd
$date
	Mon Jul 17 22:02:28 2023
$end
$version
	Icarus Verilog
$end
$timescale
	1s
$end
$scope module test_tb $end
$var wire 1 ! Ctrl0_out $end
$var parameter 32 " clk_period_p $end
$var reg 1 # ADDRESS_MODE $end
$var reg 1 $ Ctrl0 $end
$var reg 1 % INTERNAL_DEC $end
$var reg 1 & INTERNAL_INC_DEC $end
$var reg 1 ' INTERNAL_MOV $end
$scope module decode_ctrl0 $end
$var wire 1 # ADDRESS_MODE $end
$var wire 1 $ Ctrl0 $end
$var wire 1 % INTERNAL_DEC $end
$var wire 1 & INTERNAL_INC_DEC $end
$var wire 1 ' INTERNAL_MOV $end
$var wire 1 ( tmp3 $end
$var wire 1 ) tmp2 $end
$var wire 1 * tmp1 $end
$var wire 1 ! Ctrl0_out $end
$scope module NAND1 $end
$var wire 1 $ a $end
$var wire 1 # b $end
$var wire 1 * y $end
$var wire 1 + tmp $end
$scope module AND $end
$var wire 1 $ a $end
$var wire 1 # b $end
$var wire 1 + x $end
$upscope $end
$upscope $end
$scope module NAND2 $end
$var wire 1 * a $end
$var wire 1 * b $end
$var wire 1 ) y $end
$var wire 1 , tmp $end
$scope module AND $end
$var wire 1 * a $end
$var wire 1 * b $end
$var wire 1 , x $end
$upscope $end
$upscope $end
$scope module NAND3 $end
$var wire 1 ) a $end
$var wire 1 ' b $end
$var wire 1 ( y $end
$var wire 1 - tmp $end
$scope module AND $end
$var wire 1 ) a $end
$var wire 1 ' b $end
$var wire 1 - x $end
$upscope $end
$upscope $end
$scope module NAND4 $end
$var wire 1 ( a $end
$var wire 1 ( b $end
$var wire 1 ! y $end
$var wire 1 . tmp $end
$scope module AND $end
$var wire 1 ( a $end
$var wire 1 ( b $end
$var wire 1 . x $end
$upscope $end
$upscope $end
$upscope $end
$upscope $end
$enddefinitions $end
$comment Show the parameter values. $end
$dumpall
b1010 "
$end
#0
$dumpvars
1.
0-
1,
0+
1*
0)
1(
1'
1&
1%
0$
1#
0!
$end
#10
1!
0.
0(
1-
1)
0,
0*
1+
1$
#20
0!
0)
1.
1,
1(
1*
0-
0+
0'
0$
#30
1)
0,
0*
1+
1$
#40
0)
1,
1*
0+
0&
0$
#50
1)
0,
0*
1+
1$
#60
0)
1,
1*
0+
0%
0$
#70
1)
0,
0*
1+
1$
#80
0)
1,
1*
0+
1%
1&
0$
#90
1)
0,
0*
1+
1$
#100
0)
1,
1*
0+
0&
0$
#110
1)
0,
0*
1+
1$
#120
0)
1,
1*
0+
0%
0$
#130
1)
0,
0*
1+
1$
